sphinxcontrib_paradoxy-0.3.1-nspkg.pth
sphinxcontrib/paradoxy.py
sphinxcontrib_paradoxy-0.3.1.dist-info/DESCRIPTION.rst
sphinxcontrib_paradoxy-0.3.1.dist-info/METADATA
sphinxcontrib_paradoxy-0.3.1.dist-info/RECORD
sphinxcontrib_paradoxy-0.3.1.dist-info/WHEEL
sphinxcontrib_paradoxy-0.3.1.dist-info/metadata.json
sphinxcontrib_paradoxy-0.3.1.dist-info/namespace_packages.txt
sphinxcontrib_paradoxy-0.3.1.dist-info/top_level.txt
test/__init__.py
test/test_extension.py
test/basic/conf.py
test/basic/contents.rst
test/doxygen/Doxyfile
test/doxygen/Example.php
test/doxygen/Example.xml
test/doxygen/NamespacedExample.php
